[
    {
        "sentence": "Tengo hermanos.",
        "translation": "I have siblings."
    },
    {
        "sentence": "Mi hermano es mayor.",
        "translation": "My brother is older."
    },
    {
        "sentence": "Mi hermana es menor.",
        "translation": "My sister is younger."
    },



    {
        "sentence": "¿Cómo te llamas?",
        "translation": "What is your name?"
    },
    {
        "sentence": "Me llamo",
        "translation": "My name"
    },
    {
        "sentence": "De nada",
        "translation": "You're welcome"
    },
    {
        "sentence": "¿De dónde eres?",
        "translation": "Where are you from?"
    },
    {
        "sentence": "Soy de España.",
        "translation": "I am from Spain."
    },
    {
        "sentence": "¿Hablas inglés?",
        "translation": "Do you speak English?"
    },
    {
        "sentence": "No entiendo.",
        "translation": "I don't understand."
    },
    {
        "sentence": "¿Qué hora es?",
        "translation": "What time is it?"
    },
    {
        "sentence": "Son las tres de la tarde.",
        "translation": "It's three in the afternoon."
    },
    {
        "sentence": "¿Dónde está el baño?",
        "translation": "Where is the bathroom?"
    },
    {
        "sentence": "¿Cuánto cuesta esto?",
        "translation": "How much does this cost?"
    },
    {
        "sentence": "¿Puedes ayudarme?",
        "translation": "Can you help me?"
    },
    {
        "sentence": "Tengo hambre.",
        "translation": "I am hungry."
    },
    {
        "sentence": "Tengo sed.",
        "translation": "I am thirsty."
    },
    {
        "sentence": "Buenos días.",
        "translation": "Good morning."
    },
    {
        "sentence": "Buenas noches.",
        "translation": "Good night."
    },
    {
        "sentence": "¿Qué tal estás?",
        "translation": "How are you?"
    },
    {
        "sentence": "Estoy bien, gracias.",
        "translation": "I am fine, thank you."
    },
    {
        "sentence": "Me gusta esta ciudad.",
        "translation": "I like this city."
    },
    {
        "sentence": "Me gusta",
        "translation": "I like."
    },
    {
        "sentence": "No me gusta",
        "translation": "I don't like."
    },
    {
        "sentence": "¿Dónde está la estación?",
        "translation": "Where is the station?"
    },
    {
        "sentence": "¿A qué te dedicas?",
        "translation": "What do you do for a living?"
    },
    {
        "sentence": "Soy estudiante.",
        "translation": "I am a student."
    },
    {
        "sentence": "¿Qué tiempo hace?",
        "translation": "What's the weather like?"
    },
    {
        "sentence": "Hace calor hoy.",
        "translation": "It's hot today."
    },
    {
        "sentence": "Está lloviendo.",
        "translation": "It's raining."
    },
    {
        "sentence": "¿Tienes hermanos?",
        "translation": "Do you have siblings?"
    },
    {
        "sentence": "¿Cuál es tu número de teléfono?",
        "translation": "What's your phone number?"
    },
    {
        "sentence": "¿Dónde vives?",
        "translation": "Where do you live?"
    },
    {
        "sentence": "Vivo en Madrid.",
        "translation": "I live in Madrid."
    },
    {
        "sentence": "¿Cuántos años tienes?",
        "translation": "How old are you?"
    },
    {
        "sentence": "Tengo veinte años.",
        "translation": "I am twenty years old."
    },
    {
        "sentence": "¿Te gusta la música?",
        "translation": "Do you like music?"
    },
    {
        "sentence": "Me encanta bailar.",
        "translation": "I love to dance."
    },
    {
        "sentence": "¿Qué quieres comer?",
        "translation": "What do you want to eat?"
    },
    {
        "sentence": "La cuenta, por favor.",
        "translation": "The bill, please."
    },
    {
        "sentence": "¿Puedo pagar con tarjeta?",
        "translation": "Can I pay by card?"
    },
    {
        "sentence": "¿Dónde está el supermercado?",
        "translation": "Where is the supermarket?"
    },
    {
        "sentence": "Necesito ir al médico.",
        "translation": "I need to go to the doctor."
    },
    {
        "sentence": "Me duele la cabeza.",
        "translation": "My head hurts."
    },
    {
        "sentence": "¿A qué hora abre?",
        "translation": "What time does it open?"
    },
    {
        "sentence": "¿A qué hora cierra?",
        "translation": "What time does it close?"
    },
    {
        "sentence": "¿Hay WiFi aquí?",
        "translation": "Is there WiFi here?"
    },
    {
        "sentence": "¿Cuál es la contraseña?",
        "translation": "What's the password?"
    },
    {
        "sentence": "Perdón por llegar tarde.",
        "translation": "Sorry for being late."
    },
    {
        "sentence": "No hay problema.",
        "translation": "No problem."
    },
    {
        "sentence": "¿Puedo sentarme aquí?",
        "translation": "Can I sit here?"
    },
    {
        "sentence": "Este asiento está ocupado.",
        "translation": "This seat is taken."
    },
    {
        "sentence": "¿Qué día es hoy?",
        "translation": "What day is it today?"
    },
    {
        "sentence": "¿Dónde puedo comprar billetes?",
        "translation": "Where can I buy tickets?"
    },
    {
        "sentence": "¿Cuánto tiempo tarda?",
        "translation": "How long does it take?"
    },
    {
        "sentence": "¿Hay un cajero cerca?",
        "translation": "Is there an ATM nearby?"
    },
    {
        "sentence": "Me he perdido.",
        "translation": "I am lost."
    },
    {
        "sentence": "¿Puede repetir, por favor?",
        "translation": "Can you repeat, please?"
    },
    {
        "sentence": "Más despacio, por favor.",
        "translation": "Slower, please."
    },
    {
        "sentence": "No hablo español muy bien.",
        "translation": "I don't speak Spanish very well."
    },
    {
        "sentence": "¿Qué significa esta palabra?",
        "translation": "What does this word mean?"
    },
    {
        "sentence": "¿Cómo se dice ... en español?",
        "translation": "How do you say ... in Spanish?"
    },
    {
        "sentence": "Estoy aprendiendo español.",
        "translation": "I am learning Spanish."
    },
    {
        "sentence": "¿Puedo tomar una foto?",
        "translation": "Can I take a photo?"
    },
    {
        "sentence": "¿Tienes fuego?",
        "translation": "Do you have a light?"
    },
    {
        "sentence": "¿A qué hora sale el tren?",
        "translation": "What time does the train leave?"
    },
    {
        "sentence": "¿Cuál es la mejor ruta?",
        "translation": "What is the best route?"
    },
    {
        "sentence": "¿Dónde puedo aparcar?",
        "translation": "Where can I park?"
    },
    {
        "sentence": "Necesito un taxi.",
        "translation": "I need a taxi."
    },
    {
        "sentence": "¿Cuánto tiempo te quedas?",
        "translation": "How long are you staying?"
    },
    {
        "sentence": "Me quedo una semana.",
        "translation": "I'm staying for a week."
    },
    {
        "sentence": "¿Has estado aquí antes?",
        "translation": "Have you been here before?"
    },
    {
        "sentence": "Es la primera vez.",
        "translation": "It's the first time."
    },
    {
        "sentence": "¿Qué me recomiendas?",
        "translation": "What do you recommend?"
    },
    {
        "sentence": "La comida está deliciosa.",
        "translation": "The food is delicious."
    },
    {
        "sentence": "¿Tienes reserva?",
        "translation": "Do you have a reservation?"
    },
    {
        "sentence": "Una mesa para dos, por favor.",
        "translation": "A table for two, please."
    },
    {
        "sentence": "¿Puedo ver el menú?",
        "translation": "Can I see the menu?"
    },
    {
        "sentence": "Agua sin gas, por favor.",
        "translation": "Still water, please."
    },
    {
        "sentence": "¿Dónde está la farmacia?",
        "translation": "Where is the pharmacy?"
    },
    {
        "sentence": "Necesito medicinas.",
        "translation": "I need medicine."
    },
    {
        "sentence": "¿Aceptan tarjetas de crédito?",
        "translation": "Do you accept credit cards?"
    },
    {
        "sentence": "¿Hay descuentos?",
        "translation": "Are there any discounts?"
    },
    {
        "sentence": "¿Está incluido el servicio?",
        "translation": "Is service included?"
    },
    {
        "sentence": "¿Puedo probarme esto?",
        "translation": "Can I try this on?"
    },
    {
        "sentence": "¿Tiene otra talla?",
        "translation": "Do you have another size?"
    },
    {
        "sentence": "¿Dónde está el probador?",
        "translation": "Where is the fitting room?"
    },
    {
        "sentence": "Es demasiado caro.",
        "translation": "It's too expensive."
    },
    {
        "sentence": "¿Hay algo más barato?",
        "translation": "Is there anything cheaper?"
    },
    {
        "sentence": "¿Tienes cambio?",
        "translation": "Do you have change?"
    },
    {
        "sentence": "¿A qué distancia está?",
        "translation": "How far is it?"
    },
    {
        "sentence": "¿Se puede ir andando?",
        "translation": "Can we walk there?"
    },
    {
        "sentence": "¿Hay un hotel cerca?",
        "translation": "Is there a hotel nearby?"
    },
    {
        "sentence": "¿Tienen habitaciones libres?",
        "translation": "Do you have any rooms available?"
    },
    {
        "sentence": "¿Puedo ver la habitación?",
        "translation": "Can I see the room?"
    },
    {
        "sentence": "¿Incluye el desayuno?",
        "translation": "Does it include breakfast?"
    },
    {
        "sentence": "¿Hay aire acondicionado?",
        "translation": "Is there air conditioning?"
    },
    {
        "sentence": "¿Cuál es el código WiFi?",
        "translation": "What's the WiFi code?"
    },
    {
        "sentence": "¿A qué hora es el desayuno?",
        "translation": "What time is breakfast?"
    },
    {
        "sentence": "¿Dónde está el ascensor?",
        "translation": "Where is the elevator?"
    },
    {
        "sentence": "¿Puede llamarme un taxi?",
        "translation": "Can you call me a taxi?"
    },
    {
        "sentence": "Necesito cambiar dinero.",
        "translation": "I need to exchange money."
    },
    {
        "sentence": "¿Cuál es el tipo de cambio?",
        "translation": "What's the exchange rate?"
    },
    {
        "sentence": "¿Hay un banco cerca?",
        "translation": "Is there a bank nearby?"
    },
    {
        "sentence": "¿Dónde está la embajada?",
        "translation": "Where is the embassy?"
    },
    {
        "sentence": "He perdido mi pasaporte.",
        "translation": "I've lost my passport."
    },
    {
        "sentence": "¿Puede ayudarme a encontrar...?",
        "translation": "Can you help me find...?"
    },
    {
        "sentence": "¿Hay un médico que hable inglés?",
        "translation": "Is there a doctor who speaks English?"
    },
    {
        "sentence": "Es una emergencia.",
        "translation": "It's an emergency."
    },
    {
        "sentence": "Llame a una ambulancia.",
        "translation": "Call an ambulance."
    },
    {
        "sentence": "¿Dónde está la policía?",
        "translation": "Where is the police station?"
    }
]